{"type":"Topology","bbox":[13.365261,45.423637,16.515302,46.863962],"transform":{"scale":[0.0001575099254962747,0.00007201985099254969],"translate":[13.365261,45.423637]},"objects":{"states":{"type":"GeometryCollection","geometries":[{"type":"Polygon","arcs":[[0,1,2]]},{"type":"Polygon","arcs":[[3,4,5,6,7,8,9,10,11]]},{"type":"Polygon","arcs":[[12,-12,13,14,15]]},{"type":"Polygon","arcs":[[16,-16]]},{"type":"Polygon","arcs":[[-14,-11,17,18,19,20]]},{"type":"Polygon","arcs":[[-20,21,22,23]]},{"type":"Polygon","arcs":[[24,25,26,27,28]]},{"type":"Polygon","arcs":[[29,-29,30,-6,31]]},{"type":"Polygon","arcs":[[-32,-5,32]]},{"type":"Polygon","arcs":[[33,34,35,36,37]]},{"type":"Polygon","arcs":[[-38,38,39,40]]},{"type":"Polygon","arcs":[[-40,41,42,43]]},{"type":"Polygon","arcs":[[44,-43,45,46,47,48,49,50]]},{"type":"Polygon","arcs":[[51,-51,52,53]]},{"type":"Polygon","arcs":[[-54,54,55]]},{"type":"Polygon","arcs":[[56,-55,-53,-50,57,58,59,60,61]]},{"type":"Polygon","arcs":[[62,-62,63]]},{"type":"Polygon","arcs":[[64,-64,-61,65]]},{"type":"Polygon","arcs":[[-66,-60,66,67,68,69]]},{"type":"Polygon","arcs":[[70,-69,71,72,73]]},{"type":"Polygon","arcs":[[74,-74,75,76,77,78]]},{"type":"Polygon","arcs":[[-79,79,-2,80,81]]},{"type":"Polygon","arcs":[[-23,82,83,84,85]]},{"type":"Polygon","arcs":[[86,-85,87,88,89,90]]},{"type":"Polygon","arcs":[[91,-91,92,93,94,95,96,97,98]]},{"type":"Polygon","arcs":[[-99,99,100,101]]},{"type":"Polygon","arcs":[[-101,102,103,104,105,106]]},{"type":"Polygon","arcs":[[-106,107,108,109]]},{"type":"Polygon","arcs":[[110,-109,111,112,113,114,115,116,117]]},{"type":"Polygon","arcs":[[-118,118,119,120,121]]},{"type":"Polygon","arcs":[[122,123,124,125,126]]},{"type":"Polygon","arcs":[[-127,127,128,129]]},{"type":"Polygon","arcs":[[-129,130,131,132,133]]},{"type":"Polygon","arcs":[[-121,134,135,-124,136]]},{"type":"Polygon","arcs":[[137,-133,138,139,140]]},{"type":"Polygon","arcs":[[-141,141,142,143]]},{"type":"Polygon","arcs":[[144,-143,145]]},{"type":"Polygon","arcs":[[-146,-142,-140,146,147,148,149,150,151]]},{"type":"Polygon","arcs":[[152,153,154,155,156,157]]},{"type":"Polygon","arcs":[[158,-158,159,160,161]]},{"type":"Polygon","arcs":[[-162,162,-35,163]]},{"type":"Polygon","arcs":[[-151,164,165,166,167]]},{"type":"Polygon","arcs":[[-167,168,169,-154,170]]},{"type":"Polygon","arcs":[[171,172,173,174,175,176,-26]]},{"type":"Polygon","arcs":[[177,178,179,180,181,182,183,184,-173]]},{"type":"Polygon","arcs":[[185,-179]]},{"type":"Polygon","arcs":[[186,187,188,189,190,-181]]},{"type":"Polygon","arcs":[[191,192,-188]]},{"type":"Polygon","arcs":[[193,194,195,196,-189,-193]]},{"type":"Polygon","arcs":[[197,198,199,200,201,202,203,204,-195]]},{"type":"Polygon","arcs":[[205,206,-199]]},{"type":"Polygon","arcs":[[207,208,209,-200,-207]]},{"type":"Polygon","arcs":[[210,211,212,-209]]},{"type":"Polygon","arcs":[[213,214,215,216,217,-212]]},{"type":"Polygon","arcs":[[218,219,220,221,222,-215]]},{"type":"Polygon","arcs":[[223,224,225,-220]]},{"type":"Polygon","arcs":[[226,227,228,-225]]},{"type":"Polygon","arcs":[[229,230,231,232,233,234,235,-228]]},{"type":"Polygon","arcs":[[236,237,238,-231]]},{"type":"Polygon","arcs":[[239,240,241,242,243,244,245,246,-238]]},{"type":"Polygon","arcs":[[247,248,249,-241]]},{"type":"Polygon","arcs":[[250,251,252,-249]]},{"type":"Polygon","arcs":[[253,254,255,256,257,258,259,260,-252]]},{"type":"Polygon","arcs":[[261,262,-255]]},{"type":"Polygon","arcs":[[263,264,265,266,267,-256,-263]]},{"type":"Polygon","arcs":[[268,269,270,271,272,-265]]},{"type":"Polygon","arcs":[[273,-77,274,275,-270]]},{"type":"Polygon","arcs":[[276,-81,-1]]},{"type":"Polygon","arcs":[[-108,-105,277,-112]]},{"type":"Polygon","arcs":[[-114,278,279,280,281]]},{"type":"Polygon","arcs":[[-115,-282,282,283,284]]},{"type":"Polygon","arcs":[[-285,285,286,287,-116]]},{"type":"Polygon","arcs":[[288,289,-96,290,291,292,293,294,-279,-113,-278,-104]]},{"type":"Polygon","arcs":[[-103,-100,-98,295,-289]]},{"type":"Polygon","arcs":[[-120,296,297,298,299,300,-135]]},{"type":"Polygon","arcs":[[-136,-301,301,302,303,-125]]},{"type":"Polygon","arcs":[[-139,-132,304,-303,305,306,307,-147]]},{"type":"Polygon","arcs":[[-126,-304,-305,-131,-128]]},{"type":"Polygon","arcs":[[308,309,-170,310,311]]},{"type":"Polygon","arcs":[[-309,312,313,314,315]]},{"type":"Polygon","arcs":[[-312,316,317,318,-313]]},{"type":"Polygon","arcs":[[-311,-169,-166,319,320,321,322,323,324,325,326,327,-317]]},{"type":"Polygon","arcs":[[328,-315,329,330,331,332]]},{"type":"Polygon","arcs":[[-329,333,334,335,336,337,-155,-310,-316]]},{"type":"Polygon","arcs":[[-334,-333,338,339,340]]},{"type":"Polygon","arcs":[[-335,-341,341,342,-47,343]]},{"type":"Polygon","arcs":[[-336,-344,-46,-42,-39,-37,344,345]]},{"type":"Polygon","arcs":[[-338,346,-156]]},{"type":"Polygon","arcs":[[-346,347,-160,-157,-347,-337]]},{"type":"Polygon","arcs":[[-308,348,349,350,351,-148]]},{"type":"Polygon","arcs":[[-352,352,353,354,-149]]},{"type":"Polygon","arcs":[[-355,355,-320,-165,-150]]},{"type":"Polygon","arcs":[[356,357,358,-325]]},{"type":"Polygon","arcs":[[-296,-97,-290]]},{"type":"Polygon","arcs":[[359,360,361,362,363,364,365,366,367]]},{"type":"Polygon","arcs":[[-360,368]]},{"type":"Polygon","arcs":[[-288,369,-297,-119,-117]]},{"type":"Polygon","arcs":[[-330,-314,-319,370,371,372]]},{"type":"Polygon","arcs":[[-371,-318,-328,373]]},{"type":"Polygon","arcs":[[-372,-374,-327,374,375,376]]},{"type":"Polygon","arcs":[[377,378,379,380,381,382,383]]},{"type":"Polygon","arcs":[[384,-378]]},{"type":"Polygon","arcs":[[-291,-95,385,386]]},{"type":"Polygon","arcs":[[-376,387,388]]},{"type":"Polygon","arcs":[[-18,-10,389,-88,-84,390]]},{"type":"Polygon","arcs":[[-391,-83,-22,-19]]},{"type":"Polygon","arcs":[[-9,391,392,-89,-390]]},{"type":"Polygon","arcs":[[-292,-387,393,394,395,396]]},{"type":"Polygon","arcs":[[397,398,399,400,-380,401]]},{"type":"Polygon","arcs":[[-402,-379,-385,-384,402,403,-339,-332,404]]},{"type":"Polygon","arcs":[[-404,405,406,-342,-340]]},{"type":"Polygon","arcs":[[-403,-383,407,408,409,410,411]]},{"type":"Polygon","arcs":[[-397,412,-293]]},{"type":"Polygon","arcs":[[-294,-413,-396,413,414]]},{"type":"Polygon","arcs":[[-284,415,416,417,-286]]},{"type":"Polygon","arcs":[[-281,418,419,420,-416,-283]]},{"type":"Polygon","arcs":[[-323,421,422,423,424]]},{"type":"Polygon","arcs":[[425,426,427,428,-349,-307]]},{"type":"Polygon","arcs":[[-429,429,430,431,432]]},{"type":"Polygon","arcs":[[-350,-433,433,434]]},{"type":"Polygon","arcs":[[-353,-351,-435,435,436,437]]},{"type":"Polygon","arcs":[[438,439,440,441]]},{"type":"Polygon","arcs":[[-439,442,443,444,445,446]]},{"type":"Polygon","arcs":[[-442,447,-299,448,449,450,-443]]},{"type":"Polygon","arcs":[[-300,-448,-441,451,-426,-306,-302]]},{"type":"Polygon","arcs":[[452,-357,-324,-425,453,454,455]]},{"type":"Polygon","arcs":[[-456,456,457,458,459,460,461,462,463]]},{"type":"Polygon","arcs":[[-438,464,-321,-356,-354]]},{"type":"Polygon","arcs":[[465,466,-272,467,468,-408,-382,469,-400]]},{"type":"Polygon","arcs":[[-466,470,471,472,473,474,475,476]]},{"type":"Polygon","arcs":[[-381,-401,-470]]},{"type":"Polygon","arcs":[[-469,477,478,479,480,-409]]},{"type":"Polygon","arcs":[[-468,-271,-276,481,-478]]},{"type":"Polygon","arcs":[[-447,482,483,-427,-452,-440]]},{"type":"Polygon","arcs":[[-483,-446,484,485,-366,486]]},{"type":"Polygon","arcs":[[-322,-465,-437,487,-422]]},{"type":"Polygon","arcs":[[-375,-326,-359,488,489,490,-388]]},{"type":"Polygon","arcs":[[491,492,493,494,495,496]]},{"type":"Polygon","arcs":[[-492,497,498,499,-398,-405,-331,-373,-377,-389,-491,500,-462,501]]},{"type":"Polygon","arcs":[[-502,-461,502,-493]]},{"type":"Polygon","arcs":[[503,-471,-399,-500]]},{"type":"Polygon","arcs":[[-463,-501,-490,504]]},{"type":"Polygon","arcs":[[-431,505,506,507,508]]},{"type":"Polygon","arcs":[[-464,-505,-489,-358,-453]]},{"type":"Polygon","arcs":[[-496,509,-258,510,-474,511]]},{"type":"Polygon","arcs":[[-458,512,513,-363,514]]},{"type":"Polygon","arcs":[[515,-367,-486]]},{"type":"Polygon","arcs":[[-444,-451,516,517,518,519]]},{"type":"Polygon","arcs":[[-412,520,-406]]},{"type":"Polygon","arcs":[[-450,521,-517]]},{"type":"Polygon","arcs":[[-407,522,-48,-343]]},{"type":"Polygon","arcs":[[-36,-163,-161,-348,-345]]},{"type":"Polygon","arcs":[[-410,-481,523,-67,-59,524]]},{"type":"Polygon","arcs":[[-479,-482,-275,-76,-73,525]]},{"type":"Polygon","arcs":[[-411,-525,-58,-49,-523,-521]]},{"type":"Polygon","arcs":[[-480,-526,-72,-68,-524]]},{"type":"Polygon","arcs":[[-477,526,-266,-273,-467]]},{"type":"Polygon","arcs":[[-516,-485,-445,-520,527,-222,528,-234,529,-361,-369,-368]]},{"type":"Polygon","arcs":[[-221,-226,-229,530,-235,-529]]},{"type":"Polygon","arcs":[[-519,531,-216,-223,-528]]},{"type":"Polygon","arcs":[[-530,-233,532,533,-459,-515,-362]]},{"type":"Polygon","arcs":[[-245,534,535]]},{"type":"Polygon","arcs":[[-536,536,-494,-503,-460,-534,-246]]},{"type":"Polygon","arcs":[[-535,-244,537,-259,-510,-495,-537]]},{"type":"Polygon","arcs":[[-28,538,-176,539,-7,-31]]},{"type":"Polygon","arcs":[[-93,-90,540,541]]},{"type":"Polygon","arcs":[[-94,-542,542,-182,543,-394,-386]]},{"type":"Polygon","arcs":[[-27,-177,-539]]},{"type":"Polygon","arcs":[[-392,-8,-540,544,-174,-185,545]]},{"type":"Polygon","arcs":[[-546,-184,546]]},{"type":"Polygon","arcs":[[-175,-545]]},{"type":"Polygon","arcs":[[-497,-512,-473,547,-498]]},{"type":"Polygon","arcs":[[-472,-504,-499,-548]]},{"type":"Polygon","arcs":[[548,-364,-514]]},{"type":"Polygon","arcs":[[-487,-365,549,-506,-430,-428,-484]]},{"type":"Polygon","arcs":[[-513,-457,-455,550,-507,-550,-549]]},{"type":"Polygon","arcs":[[-423,-488,-436,-434,-432,-509,551]]},{"type":"Polygon","arcs":[[-424,-552,-508,-551,-454]]},{"type":"Polygon","arcs":[[-236,-531]]},{"type":"Polygon","arcs":[[-420,552,-203,553]]},{"type":"Polygon","arcs":[[-295,-415,554,555,556,-204,-553,-419,-280]]},{"type":"Polygon","arcs":[[-213,-218,557,558,-201,-210]]},{"type":"Polygon","arcs":[[-518,-522,-449,-298,-370,-287,-418,559,-558,-217,-532]]},{"type":"Polygon","arcs":[[-205,-557,560,-196]]},{"type":"Polygon","arcs":[[-417,-421,-554,-202,-559,-560]]},{"type":"Polygon","arcs":[[-197,-561,-556,561,-190]]},{"type":"Polygon","arcs":[[-393,-547,-183,-543,-541]]},{"type":"Polygon","arcs":[[-395,-544,-191,-562,-555,-414]]},{"type":"Polygon","arcs":[[-250,-253,-261,562,-242]]},{"type":"Polygon","arcs":[[-243,-563,-260,-538]]},{"type":"Polygon","arcs":[[-476,563,-267,-527]]},{"type":"Polygon","arcs":[[-475,-511,-257,-268,-564]]},{"type":"Polygon","arcs":[[-247,-533,-232,-239]]}]}},"arcs":[[[1560,1588],[48,-228],[23,-206],[72,-99],[52,-139],[31,-20],[69,55],[34,206]],[[1889,1157],[171,-104],[22,-57],[-98,-173],[-44,-162],[-60,-66],[-9,-90]],[[1871,505],[-108,-8],[-120,46],[-219,362],[-3,178],[44,143],[0,86],[-110,73],[-64,220],[133,-48],[136,31]],[[18629,18826],[6,-103],[87,-399],[72,-140],[55,-160],[59,-105],[88,23],[2,-233],[49,-32]],[[19047,17677],[-58,-167]],[[18989,17510],[-98,58],[-85,-177],[-63,-213],[-20,-217]],[[18723,16961],[-104,37]],[[18619,16998],[-92,113],[-44,19],[-50,-81],[-177,29]],[[18256,17078],[-94,26],[-142,111],[-73,119],[-3,103],[-82,252]],[[17862,17689],[-19,293],[55,117],[36,1],[130,247]],[[18064,18347],[84,26],[53,142],[54,73],[109,246]],[[18364,18834],[208,-41],[57,33]],[[18703,19076],[-57,-145],[-17,-105]],[[18364,18834],[55,304],[-7,106],[-41,116],[-91,137],[-107,90],[-306,336]],[[17867,19923],[587,76],[65,-56],[97,-179]],[[18616,19764],[36,-159],[0,-184],[-46,-169],[15,-85],[82,-91]],[[18616,19764],[84,-98],[93,-7],[28,-70],[-50,-294],[-68,-219]],[[18064,18347],[-109,240],[67,273],[-38,162],[-90,55],[-122,179],[-24,104],[-68,120],[-87,40]],[[17593,19520],[-71,49]],[[17522,19569],[-14,144],[46,185]],[[17554,19898],[33,-12],[280,37]],[[17522,19569],[-167,-13],[-43,-26],[-125,-158],[-104,-38]],[[17083,19334],[-19,416]],[[17064,19750],[260,233],[230,-85]],[[19091,16838],[26,-100],[116,-140],[226,-203],[234,-551],[214,-276],[92,-599],[-154,187],[-129,71],[-138,-27],[-108,68],[-107,171],[-56,55],[-234,15],[-73,89],[-40,-104],[-48,104],[-24,-44]],[[18888,15554],[-74,68],[37,108]],[[18851,15730],[103,16],[106,73],[191,212],[-121,300]],[[19130,16331],[-194,216]],[[18936,16547],[121,262],[34,29]],[[19284,17210],[-38,-55],[-121,-87],[-58,-137],[24,-93]],[[18936,16547],[-213,414]],[[18989,17510],[49,-137],[59,-67],[123,-79],[64,-17]],[[19047,17677],[157,-36],[95,-96],[35,-262],[-50,-73]],[[2035,14446],[17,52],[9,355],[35,73],[36,184],[-1,110],[96,-13],[420,-154],[86,2],[412,102],[192,-48],[581,-415],[104,-19],[103,28]],[[4125,14703],[-17,-304],[-80,-107],[-47,-113]],[[3981,14179],[-81,-36],[-46,-84],[-159,-145],[-185,-253],[-446,-365]],[[3064,13296],[-39,13]],[[3025,13309],[-112,215],[-81,213],[-80,97],[-199,182],[-184,100],[-164,-111],[-131,-41],[-31,34],[20,308],[-28,140]],[[3025,13309],[-87,-181],[-406,-334],[-92,-136],[-47,-128],[-94,-338]],[[2299,12192],[-355,-94],[-127,19],[-140,59],[-286,-13],[-217,34],[-113,-56],[-40,-51],[27,-113],[-19,-66],[-77,-59],[-242,53],[-178,86],[-191,114],[-148,157]],[[193,12262],[90,234],[85,295],[69,125],[84,14],[79,58],[152,168],[294,239],[155,245],[135,287],[155,222],[216,43],[157,-9],[118,97],[53,166]],[[2299,12192],[59,-216]],[[2358,11976],[-114,-24],[-62,-98],[-44,-119],[-61,-418],[-45,-65],[-164,-24],[-100,-93],[-60,29],[-65,-121],[-8,-256],[89,-131],[-60,-130]],[[1664,10526],[-85,25],[-187,-31],[-162,39],[-191,288],[-119,127],[-177,54],[-89,77],[-190,20],[-99,52],[93,-245],[-173,-41],[-54,120],[-22,193],[-86,177],[-38,348],[-36,165],[-49,140],[165,156],[28,72]],[[1751,10383],[-23,125],[-64,18]],[[2358,11976],[216,-336],[319,-280],[284,-140],[186,-24],[648,129]],[[4011,11325],[51,-176],[-1,-93],[-99,-351]],[[3962,10705],[-199,-225],[-218,-107],[-108,-99],[-83,-130],[-47,-197],[26,-211],[59,-162],[12,-218],[41,-293],[-6,-44],[-76,-77]],[[3363,8942],[-46,16],[-35,-76],[-94,21],[-41,-85],[64,-122],[23,-96],[-41,-31],[-15,-469]],[[3178,8100],[-175,170],[-113,233],[-58,194],[-22,171],[1,265],[-51,309],[-45,69],[-77,5],[-75,-102]],[[2563,9414],[-384,367],[-137,249],[-12,104],[-117,301],[-162,-52]],[[999,9048],[595,691],[182,509],[-25,135]],[[2563,9414],[-13,-274],[-97,-240],[-75,-89],[-49,-4],[-171,109],[-151,17],[-92,-77],[-76,-94],[-192,-431],[120,-262],[-70,-46],[-110,141],[-72,18]],[[1515,8182],[-106,210],[-102,146],[-93,280],[-66,104],[-91,57],[-58,69]],[[1515,8182],[141,-226],[-96,-76],[-65,-91]],[[1495,7789],[-185,-66],[-204,-150],[-191,-22],[-302,541],[130,167],[49,99],[18,96],[-16,90],[-51,81],[145,295],[111,128]],[[1588,7252],[47,284],[-107,264],[-33,-11]],[[3178,8100],[-86,-69]],[[3092,8031],[-52,-120],[0,-134],[-287,-318],[-156,-401],[-135,-245],[-129,-117],[91,-105],[51,-96],[88,-85],[114,-174],[114,-232],[100,-88],[85,-197]],[[2976,5719],[-140,90],[-205,-15],[-110,50],[-338,284]],[[2183,6128],[-190,49],[-88,-7],[-166,88],[-119,162],[33,71],[88,21],[47,63]],[[1788,6575],[125,179],[126,73],[-1,145],[-88,50],[-76,8],[-134,151],[-152,71]],[[1486,6785],[57,198],[45,269]],[[1788,6575],[-211,95],[-91,115]],[[1326,5490],[-52,157],[21,475],[191,663]],[[2183,6128],[-17,-258],[-79,-140],[-76,-64],[-76,-126],[-134,-36],[-361,16],[-114,-30]],[[2976,5719],[152,-125],[177,30]],[[3305,5624],[106,-256]],[[3411,5368],[-316,-148],[-633,-121],[-135,7],[-165,-162],[-37,-127]],[[2125,4817],[-252,298],[-106,50],[-218,41],[-178,148],[-45,136]],[[3355,2918],[-61,19],[-95,83],[-68,114],[-506,1306],[-440,304],[-60,73]],[[3411,5368],[183,-236],[331,-282],[41,-110]],[[3966,4740],[-91,-230],[-120,-118],[-7,-93],[78,-388],[-35,-100],[-164,-385],[45,-128],[-34,-257]],[[3638,3041],[-187,16],[-96,-139]],[[3191,2479],[122,230],[42,209]],[[3638,3041],[80,-93],[130,-40],[104,-82],[117,-130],[119,-89],[94,-124],[126,-40],[79,55],[33,88],[80,58]],[[4600,2644],[94,-130],[-69,-252],[-27,-165],[27,-100],[75,-21],[-18,-216],[-52,-267],[-47,-183],[13,-37],[146,-194],[39,-133],[-10,-261]],[[4771,685],[-151,13],[-167,88],[-159,179],[-84,132],[-92,74],[-168,55]],[[3950,1226],[-23,106],[-201,366],[-265,85],[-100,107],[-93,176],[-77,413]],[[3950,1226],[-99,32],[-44,-45],[-22,-99],[0,-149],[135,-247],[-82,-172],[-297,-194],[-93,-140],[-55,-135],[-68,-77],[-339,76],[-100,49],[-84,132],[-300,292],[-631,-44]],[[1889,1157],[73,191],[5,334]],[[1967,1682],[494,113],[0,85],[-67,149],[-194,325],[313,43],[250,-209],[300,48],[128,243]],[[17083,19334],[-28,-561],[3,-77],[73,-83]],[[17131,18613],[-51,-114]],[[17080,18499],[-195,42],[-40,37],[-86,172],[-109,25],[-107,-11]],[[16543,18764],[46,474],[-5,98],[-34,61],[99,131],[282,104],[133,118]],[[16834,17315],[-14,320],[-72,215],[-135,130],[-73,340],[-5,243],[8,201]],[[17080,18499],[15,-286],[-29,-216],[37,-147],[47,-67],[111,-66],[53,-65],[101,-63]],[[17415,17589],[-33,-189],[34,-212],[93,-245],[-17,-96],[-64,-182]],[[17428,16665],[-274,284],[-162,256]],[[16992,17205],[-88,32],[-70,78]],[[16522,17647],[123,-33],[69,-73],[120,-226]],[[16992,17205],[-215,-415],[-6,-159],[43,-385]],[[16814,16246],[-224,-107]],[[16590,16139],[-143,31]],[[16447,16170],[-143,114]],[[16304,16284],[-107,200],[-20,184],[96,131],[17,66],[-52,34],[-87,-12],[-134,84]],[[16017,16971],[3,235]],[[16020,17206],[276,33],[94,129],[132,279]],[[16020,17206],[-75,77],[-114,45],[-200,205],[-57,136],[-89,50]],[[15485,17719],[-125,173]],[[15360,17892],[243,147],[177,23],[176,-52],[431,-327],[135,-36]],[[15485,17719],[-3,-239],[-30,-167],[-40,-67],[10,-152],[37,-109]],[[15459,16985],[-138,18],[-33,-68],[-17,-125]],[[15271,16810],[-137,291],[-65,95],[-52,156],[-90,39],[-158,4],[-83,-268],[-4,-114],[-34,-40],[-170,-45]],[[14478,16928],[-148,332],[-4,159]],[[14326,17419],[71,159],[0,179],[19,209],[103,-93],[486,-109],[168,14],[187,114]],[[14478,16928],[118,-545],[-109,-131]],[[14487,16252],[-103,117],[-23,99],[-231,288],[-128,-6],[-215,88],[-105,158]],[[13682,16996],[66,224],[97,112],[136,54],[135,3],[96,-41],[114,71]],[[13642,16786],[40,210]],[[14487,16252],[208,-18],[121,-185],[138,-141],[153,-11],[63,66]],[[15170,15963],[92,-193],[-98,-172]],[[15164,15598],[-99,-199],[-95,-78],[-20,-80],[74,-230]],[[15024,15011],[-223,103]],[[14801,15114],[-559,62],[-284,-94]],[[13958,15082],[-86,113],[64,613]],[[13936,15808],[-74,141],[-10,220],[-96,120],[-48,133],[2,104],[-29,186],[-39,74]],[[13936,15808],[-408,-338],[-84,-46],[-157,57],[10,159]],[[13297,15640],[13,253],[-27,117],[-89,111]],[[13194,16121],[-55,108],[41,377],[-37,105]],[[13143,16711],[173,-174],[190,51],[118,140],[18,58]],[[11474,16908],[205,-33],[812,64]],[[12491,16939],[-23,-338],[-52,-64],[-146,-95],[-85,-128],[-90,-361]],[[12095,15953],[-318,-302],[-63,-105],[-8,-106],[-62,-89]],[[11644,15351],[-119,66],[-32,119],[17,161],[58,204],[-22,117],[113,65],[52,139],[11,135],[-53,91],[-72,61],[-53,95]],[[11544,16604],[3,85],[-73,219]],[[11544,16604],[-185,-220],[-90,-53],[-92,20]],[[11177,16351],[-133,145],[-101,315],[-20,187]],[[10923,16998],[551,-90]],[[11177,16351],[-88,-36],[-51,-165],[14,-105],[-17,-127]],[[11035,15918],[-206,-274],[-68,-122],[-73,43],[-153,-90],[-90,171]],[[10445,15646],[24,120],[-43,137],[-162,181],[-100,207],[-38,39],[-107,14],[-151,198]],[[9868,16542],[89,85],[91,-26],[122,-264],[236,508],[366,177],[151,-24]],[[13194,16121],[-48,-137],[-66,5],[-114,114],[-122,62],[-78,12],[-44,-66],[-16,-210],[-115,-243],[-59,-234],[-64,-135],[-40,-196]],[[12428,15093],[-35,234],[21,139],[-119,127],[-53,145],[-147,215]],[[12491,16939],[352,28],[187,-106],[113,-150]],[[9706,16406],[162,136]],[[10445,15646],[-42,-258],[-10,-245],[-24,-117],[-75,-138],[-134,-89]],[[10160,14799],[-141,19],[-123,194]],[[9896,15012],[152,230],[18,128],[-22,50],[-4,319],[-26,122],[-69,47],[-79,239],[-66,92],[-50,19],[-44,148]],[[9896,15012],[-155,-5]],[[9741,15007],[19,168],[-132,199],[-23,156],[-71,71],[-23,66],[-239,9],[-71,-18]],[[9201,15658],[49,225],[72,234],[107,233],[80,51],[89,-17],[108,22]],[[9088,15215],[67,231],[46,212]],[[9741,15007],[-31,-93],[-135,-6],[-139,69],[-128,156],[-220,82]],[[10160,14799],[-59,-411]],[[10101,14388],[-3,-175],[-88,-101],[-319,-228]],[[9691,13884],[-556,22]],[[9135,13906],[-181,94],[-36,-9],[-97,-136]],[[8821,13855],[-133,290],[-74,78],[-294,88],[-20,76]],[[8300,14387],[47,-13],[45,172],[144,295],[105,73],[57,-61],[163,41],[140,97],[35,47],[52,177]],[[5568,14088],[761,-33],[214,71],[68,-23],[86,-208],[108,-76]],[[6805,13819],[-92,-311],[-24,-132],[-67,-194],[-18,-297]],[[6604,12885],[-292,-11],[-57,-34],[-128,-161],[-26,-214]],[[6101,12465],[-162,-33],[-73,47],[-140,52]],[[5726,12531],[-44,59],[-74,319],[42,512],[-15,323],[-93,164]],[[5542,13908],[26,180]],[[4969,14118],[599,-30]],[[5542,13908],[-95,-49],[-55,-66],[-91,-183],[-61,-235],[-66,-71],[-133,-1],[-138,-133]],[[4903,13170],[-106,286],[45,196]],[[4842,13652],[9,254],[54,125],[64,87]],[[4842,13652],[-167,-45],[-125,78],[-58,74],[-511,420]],[[4125,14703],[111,30],[111,-4],[104,-47],[93,-71],[357,-465],[68,-28]],[[8821,13855],[-92,-200],[18,-197],[-105,-131],[-362,-262],[-187,25]],[[8093,13090],[-192,-61],[-89,-8],[-172,103]],[[7640,13124],[-41,318]],[[7599,13442],[84,389],[94,204],[61,38],[138,19],[130,93],[127,201],[67,1]],[[7640,13124],[-208,-118]],[[7432,13006],[-423,55],[-93,36],[-90,-30],[-41,-130],[-44,-67],[-137,15]],[[6805,13819],[88,-61],[106,-25],[219,79],[87,-181],[71,-238],[84,-133],[111,74],[28,108]],[[18888,15554],[-66,-116],[-122,-62]],[[18700,15376],[-118,52],[-67,173],[-86,-103],[-88,106],[-42,89]],[[18299,15693],[117,212]],[[18416,15905],[86,103],[48,23],[81,156],[4,110]],[[18635,16297],[178,-188]],[[18813,16109],[38,-86],[22,-191],[-22,-102]],[[18700,15376],[-58,-55]],[[18642,15321],[-152,95],[-114,-202],[8,-80]],[[18384,15134],[-165,-281],[-5,-117]],[[18214,14736],[-78,-132],[-73,11],[-54,-38],[-65,146],[-133,163],[-95,-35],[-51,-66],[-71,11],[-145,92],[-292,80],[-103,65],[-197,69]],[[16857,15102],[39,143],[2,130],[47,114],[72,85],[204,-47]],[[17221,15527],[127,-40],[156,-139],[202,-50],[75,33],[51,72],[30,236],[-30,57],[17,83]],[[17849,15779],[87,88],[88,22],[80,225]],[[18104,16114],[195,-421]],[[18642,15321],[-239,-155],[-19,-32]],[[18214,14736],[21,-276],[76,-382],[-8,-336],[18,-116],[38,-70],[109,-109],[29,-66],[10,-154],[-30,-43],[-145,4],[-226,-84],[-161,33],[-90,81],[-153,220],[-61,45],[-78,-22],[-102,-192],[-60,-77],[-111,-9]],[[17290,13183],[-82,158]],[[17208,13341],[-62,273],[-97,288],[-156,103]],[[16893,14005],[83,236],[6,269],[-121,306]],[[16861,14816],[-44,234],[40,52]],[[17290,13183],[-195,62],[-3,-248],[14,-380],[-62,-216]],[[17044,12401],[-46,243],[-28,237],[-43,97],[0,81],[59,215],[92,117],[130,-50]],[[17044,12401],[-69,-115],[-126,-134],[-162,-114]],[[16687,12038],[-29,66],[-88,449],[6,108],[-56,190],[12,177]],[[16532,13028],[124,55],[62,99],[-11,115],[-51,173],[-36,318]],[[16620,13788],[79,169],[104,85],[90,-37]],[[16687,12038],[-285,-89],[-189,-158]],[[16213,11791],[-16,141],[13,76],[-3,193],[-55,236],[27,115],[-20,146],[-63,73],[-131,97],[-96,17],[-174,-89],[-57,-160],[4,-88],[-25,-262]],[[15617,12286],[-152,168]],[[15465,12454],[77,255],[-69,222]],[[15473,12931],[104,58],[37,173],[43,323]],[[15657,13485],[120,-180],[122,30]],[[15899,13335],[170,178],[49,-45]],[[16118,13468],[155,-93],[43,-49],[47,-192],[55,-51],[114,-55]],[[16213,11791],[-224,-186],[-18,-1]],[[15971,11604],[-37,92],[-52,219],[-30,29],[-235,342]],[[15971,11604],[-296,-14],[-101,-39],[-119,-96]],[[15455,11455],[-264,186]],[[15191,11641],[24,330],[71,166],[179,317]],[[15455,11455],[-66,-77],[-129,-329],[-121,-120],[-456,52]],[[14683,10981],[2,76],[86,241],[61,60],[44,140],[85,106],[124,93]],[[15085,11697],[106,-56]],[[14683,10981],[-106,12],[-136,-107],[-84,-173]],[[14357,10713],[-85,126]],[[14272,10839],[-39,218],[-65,76],[-70,147],[-127,523]],[[13971,11803],[35,76],[105,68],[134,-3],[280,-141],[202,5]],[[14727,11808],[120,-137],[238,26]],[[14357,10713],[-141,-391],[-92,-394],[0,-349],[88,-313],[126,-202]],[[14338,9064],[-102,-147]],[[14236,8917],[-54,46],[-24,133],[26,101],[-94,313],[-57,48],[-106,138],[-78,26],[-67,91]],[[13782,9813],[60,344]],[[13842,10157],[140,133],[71,201],[219,348]],[[14338,9064],[128,-152],[177,-112],[78,-87],[57,-132]],[[14778,8581],[-53,-23],[-107,-189]],[[14618,8369],[-28,81],[-157,1],[-120,119],[-77,347]],[[14778,8581],[32,-75],[-28,-145],[-74,-170],[-49,-283],[18,-713],[-9,-231],[-78,-338],[-25,-167],[27,-177],[75,-279],[4,-198],[-64,-139],[-130,-105],[-124,-55],[-246,-13],[-238,62]],[[13869,5555],[-32,91],[-140,313],[-62,196],[-18,212],[33,165],[94,90],[103,38],[65,68],[15,119],[51,47],[33,230],[-5,493],[78,302]],[[14084,7919],[89,7],[166,128],[279,315]],[[13869,5555],[-167,43],[-61,-47],[-118,-149],[-63,-35],[-216,69],[-70,-51],[-30,-130],[35,-277],[-72,-90]],[[13107,4888],[-36,58],[-146,418],[-27,355],[-8,301],[-47,269],[-172,100]],[[12671,6389],[-66,110],[16,109],[6,235],[56,254]],[[12683,7097],[55,227],[114,257],[220,338],[33,93],[-10,166],[-33,73],[-38,212],[23,233],[-12,186]],[[13035,8882],[471,61]],[[13506,8943],[158,-109],[47,-8],[82,-92],[68,-119],[69,-375]],[[13930,8240],[34,-237],[120,-84]],[[13107,4888],[-627,-322]],[[12480,4566],[-67,416],[-147,346],[-115,180],[-33,133],[-17,166],[61,193],[145,121]],[[12307,6121],[163,142],[118,-67],[49,59],[34,134]],[[12480,4566],[-173,-88],[-255,-219],[-54,-96],[-33,-135]],[[11965,4028],[-138,-153]],[[11827,3875],[-237,-254],[-122,-28],[-98,12],[-190,-19],[-149,35]],[[11031,3621],[19,116],[81,81],[35,114],[-62,160],[-214,358],[-28,141],[-84,196],[-31,176]],[[10747,4963],[178,348]],[[10925,5311],[65,56],[31,72],[52,21],[57,169],[2,188],[105,91],[61,336]],[[11298,6244],[254,-81],[159,88],[50,80],[70,225],[-9,184],[71,212]],[[11893,6952],[190,-242],[127,-116],[112,-240],[-28,-89],[13,-144]],[[11965,4028],[6,-84],[108,-128],[63,-187],[90,-131],[83,-47],[63,121],[101,51],[134,-229],[104,-264],[35,-123],[-132,2],[-167,-112],[-186,-91],[-61,-214],[-122,-120],[6,-114],[80,-305]],[[12170,2053],[-132,151],[-79,220],[-63,-25],[-97,49],[8,116]],[[11807,2564],[107,33],[108,152],[39,156],[44,70],[46,9],[33,161],[-62,181],[-63,137],[-87,115],[-92,295],[-53,2]],[[12170,2053],[41,-374],[51,-300],[91,-237],[320,-331],[-61,-82],[-114,-245],[-55,-79],[-71,-32],[-206,7],[-618,-353],[-285,62],[-465,609]],[[10798,698],[56,209],[75,142],[108,100],[92,33],[16,107],[-49,53],[-73,-12],[-138,-68],[-63,116],[21,158],[55,114],[52,55],[67,-5],[0,63],[-108,180],[1,155],[-29,128],[5,82],[-40,168]],[[10846,2476],[202,-104],[176,26],[82,60],[62,137],[115,96],[208,-40],[116,-87]],[[10798,698],[-63,83],[-309,13],[-63,89],[-128,62]],[[10235,945],[-77,276],[-136,192],[-89,0],[-102,-48],[-76,-8],[-105,39],[-95,85],[-76,-7],[-62,-78],[-64,-274],[-46,-66],[-89,22],[-135,245],[-253,362],[-107,119],[-48,163],[13,92],[-23,53],[-41,295]],[[8624,2407],[-80,432],[99,134],[33,128]],[[8676,3101],[146,-103],[101,32],[45,95],[66,205],[7,148],[210,746],[-168,212]],[[9083,4436],[113,202]],[[9196,4638],[84,-1],[56,41],[68,-13],[148,-102],[46,-116],[119,17],[194,334],[82,33],[272,-73]],[[10265,4758],[10,-238],[-22,-107],[-52,-415],[58,-208],[247,-438],[29,-244],[82,-224]],[[10617,2884],[120,-340],[109,-68]],[[10235,945],[-94,20],[-109,158],[-145,145],[-115,-7],[-23,-296],[-122,-324],[-272,-150],[-264,86],[-102,391],[-589,398],[-126,166],[20,317],[-12,108],[-39,78]],[[8243,2035],[108,84],[273,288]],[[8243,2035],[-85,64],[-217,267],[-82,132],[-59,176],[-6,187],[8,255],[-14,213],[-70,61],[-75,-49]],[[7643,3341],[-67,237],[-12,151],[-122,586]],[[7442,4315],[80,54],[35,-50],[131,9]],[[7688,4328],[144,-81],[132,-9],[64,-59],[105,-238]],[[8133,3941],[133,-251],[59,-87],[200,-105],[147,-115],[26,-108],[-22,-174]],[[7643,3341],[-82,-105],[-80,-281],[-67,-149],[-160,-276],[-59,-134],[-45,-236]],[[7150,2160],[-111,17],[-222,4],[28,96],[-14,172],[-83,120],[-40,114],[28,377]],[[6736,3060],[-3,244],[-58,127],[-148,258],[-45,252]],[[6482,3941],[154,36],[431,525]],[[7067,4502],[189,-233],[109,-30],[77,76]],[[7150,2160],[-26,-314],[-33,-196],[-84,-234],[-249,-281],[-117,-169],[-244,-213],[-292,-41],[-295,86],[-253,170],[-139,53],[-162,-73],[-302,-218],[-183,-45]],[[4600,2644],[5,141]],[[4605,2785],[78,-20],[157,106],[154,14],[268,-26],[207,53],[126,150],[248,151],[199,62],[72,61],[28,111],[93,4],[138,-173],[60,-107],[303,-111]],[[1560,1588],[407,94]],[[15271,16810],[-63,-269],[-18,-170],[13,-202],[-33,-206]],[[15164,15598],[139,13],[59,-41],[38,-144],[117,-129],[53,-145],[-46,-120],[37,-124]],[[15561,14908],[-62,-165],[-75,-75],[-84,-171]],[[15340,14497],[-158,250],[-90,59],[-59,184]],[[15033,14990],[-9,21]],[[15033,14990],[-62,-160],[60,-240],[-101,-200]],[[14930,14390],[-47,69]],[[14883,14459],[-91,301],[34,159],[-38,110],[13,85]],[[14883,14459],[-212,-65],[-110,-6],[-74,40],[-66,83],[-151,110],[-166,0],[-98,63],[-162,28]],[[13844,14712],[-41,198]],[[13803,14910],[155,172]],[[15459,16985],[115,-20],[32,-74],[33,-175],[5,-118],[98,-137],[76,-25],[39,50]],[[15857,16486],[79,-70],[145,-300],[108,21],[115,147]],[[16447,16170],[-187,-203],[-43,-115],[56,-325]],[[16273,15527],[-27,-104]],[[16246,15423],[-203,167],[-122,-118],[-34,-58],[-68,-249],[-16,-132]],[[15803,15033],[-197,-158]],[[15606,14875],[-45,33]],[[16017,16971],[-85,-131],[-57,-183],[-18,-171]],[[13297,15640],[-62,-113],[-5,-144],[-54,-181],[-162,-264],[-44,-302]],[[12970,14636],[-171,-123],[-28,8],[-112,149],[-153,-38]],[[12506,14632],[-123,66]],[[12383,14698],[-23,143]],[[12360,14841],[68,252]],[[12360,14841],[-341,43],[-128,-13],[-98,32],[-172,194]],[[11621,15097],[-44,87]],[[11577,15184],[67,167]],[[11035,15918],[62,-141],[89,-111],[102,-255],[289,-227]],[[11621,15097],[-61,-265],[-152,-334],[-69,-105],[-11,-146],[-32,-64],[-61,-16],[-72,-305]],[[11163,13862],[-74,122],[-125,47],[-18,-107]],[[10946,13924],[-568,283],[-277,181]],[[6996,12052],[-317,-38]],[[6679,12014],[-176,33],[-62,-28],[-54,59],[-28,142],[13,35],[88,-38],[41,119],[28,196],[75,353]],[[7432,13006],[61,-106],[-6,-224],[55,-211],[-58,-130]],[[7484,12335],[-182,-169],[-92,-45],[-109,-5],[-105,-64]],[[6996,12052],[-115,-213],[-33,-129],[-11,-164],[15,-444],[117,-237]],[[6969,10865],[28,-101],[-55,-78]],[[6942,10686],[-331,-21]],[[6611,10665],[-149,455],[9,81],[50,141],[62,364],[81,173],[15,135]],[[7484,12335],[-2,-184],[42,-130],[19,-149],[105,-239],[-37,-197],[-73,-56]],[[7538,11380],[-329,-560]],[[7209,10820],[-240,45]],[[8093,13090],[43,-451],[151,-323],[61,-278],[34,-58],[128,7]],[[8510,11987],[-11,-238],[64,-93],[248,-122],[226,-18],[143,19],[277,-21]],[[9457,11514],[191,-171]],[[9648,11343],[287,-302],[-127,-115]],[[9808,10926],[-71,-26]],[[9737,10900],[-718,-123],[-102,-54],[-134,1],[-208,86],[-209,-42]],[[8366,10768],[-160,104],[-79,-28],[-85,-102],[-143,-122],[-123,9]],[[7776,10629],[-65,46],[18,78]],[[7729,10753],[-81,233],[-28,184],[-82,210]],[[6530,10229],[130,142],[-49,294]],[[6942,10686],[67,-691]],[[7009,9995],[-56,-132],[-90,-78],[-83,1],[-68,-74],[-12,-78],[110,-278],[-186,-202]],[[6624,9154],[-233,100],[-137,-93],[-77,49],[-83,158]],[[6094,9368],[35,209],[-18,73],[20,115],[44,107],[124,149],[128,67],[42,111],[61,30]],[[6530,10229],[-55,223],[-34,71],[-99,23],[8,172],[-101,-43],[-73,6],[-395,249],[-40,50],[1,70],[53,101],[-17,102],[-170,123]],[[5608,11376],[-169,104],[-88,74],[-101,171],[-163,184]],[[5087,11909],[80,39]],[[5167,11948],[310,-126],[40,-26],[256,24]],[[5773,11820],[151,-92],[170,-188],[49,83],[12,135],[-29,95],[-118,222],[6,102],[102,187],[-15,101]],[[6094,9368],[-367,113],[-224,-91],[-133,-163]],[[5370,9227],[-19,125],[-47,74],[-4,243],[44,140],[-42,152],[51,196],[39,56],[53,162],[-63,116],[-55,23],[-196,-36],[-73,16]],[[5058,10494],[50,129],[133,69],[51,73],[169,110],[32,53],[30,243],[49,76],[36,129]],[[5058,10494],[-408,-126],[-152,-170]],[[4498,10198],[-40,128],[-170,81],[-239,35],[-92,69],[5,194]],[[4011,11325],[80,100],[124,50],[357,-85],[52,35],[34,291],[74,193],[143,35],[212,-35]],[[3064,13296],[197,-205],[129,2],[304,-94],[108,-104],[121,-65],[96,-135],[70,-21],[83,-84],[134,-210],[91,-44],[141,63],[42,-8],[67,-209],[28,-28],[60,108]],[[4735,12262],[308,-53],[76,28],[55,-86],[-7,-203]],[[5773,11820],[-54,309],[7,402]],[[4735,12262],[33,159],[81,108],[45,147],[93,142],[9,70],[-93,282]],[[10946,13924],[-10,-369],[-35,-190],[-79,-200],[-20,-279]],[[10802,12886],[-176,53],[-159,124],[-89,178]],[[10378,13241],[17,129],[-57,110],[-51,18],[-86,-32],[-141,46],[-65,63],[-237,-103]],[[9758,13472],[-8,330],[-59,82]],[[9758,13472],[-131,-575],[-1,-206],[-92,-307]],[[9534,12384],[-120,8],[-238,291],[-82,88],[-107,-68]],[[8987,12703],[166,694],[13,148],[-21,135],[-10,226]],[[8987,12703],[-314,-385],[-163,-331]],[[9737,10900],[18,-245],[-58,-163],[-44,-28],[-418,-74],[54,-162]],[[9289,10228],[-151,69],[-206,44],[-268,-85],[-119,-145],[-174,-109]],[[8371,10002],[-49,94],[-74,42],[-82,107],[6,123],[70,213],[124,187]],[[12734,9888],[74,-383]],[[12808,9505],[-23,-144],[7,-120],[-74,-237]],[[12718,9004],[-328,-48],[-90,-55],[-67,-78],[-51,41],[-19,131],[-78,114],[-94,51],[-320,5],[-61,-21],[-1,-51],[70,-168],[-18,-79]],[[11661,8846],[-245,441]],[[11416,9287],[-84,62],[-51,131],[44,51],[153,-108],[75,70],[22,123],[-52,180],[-133,272],[-156,177],[-23,81],[-113,223]],[[11098,10549],[401,16],[175,52],[78,138]],[[11752,10755],[12,-71],[69,-16],[123,77],[103,-51],[233,-68]],[[12292,10626],[10,-93],[-26,-87],[-64,-82],[32,-64],[117,11],[324,209]],[[12685,10520],[74,-188],[-11,-134],[-39,-117],[25,-193]],[[12734,9888],[205,228],[54,-2],[65,-149],[82,-87],[34,-90],[-19,-124],[-36,-18],[-73,102],[-138,-225],[-100,-18]],[[13803,14910],[-247,25],[-586,-299]],[[7209,10820],[152,-358],[83,-41]],[[7444,10421],[-5,-178],[-58,-62],[-25,-91],[-63,-66]],[[7293,10024],[-170,-83],[-69,-11],[-45,65]],[[7729,10753],[-285,-332]],[[7776,10629],[-40,-176],[38,-400]],[[7774,10053],[-439,-212]],[[7335,9841],[-42,183]],[[5579,8284],[15,-100],[-47,-57],[41,-104],[139,-96],[60,15],[5,88],[197,71],[212,96]],[[6201,8197],[111,93],[46,94],[118,66]],[[6476,8450],[73,-112],[4,-184],[-73,-41],[-87,-194],[20,-188],[-62,-208]],[[6351,7523],[-136,-60],[-40,-88],[-26,-160],[24,-246],[127,-504],[119,-247]],[[6419,6218],[-73,-55],[-249,275],[-103,55],[-65,-77]],[[5929,6416],[-85,301],[-161,303],[-136,211],[-57,60],[-100,52],[-21,65],[39,149],[-10,104],[28,192],[63,81],[-152,155],[-61,26],[-37,231]],[[5239,8346],[340,-62]],[[5579,8284],[-4,156],[59,114],[189,81],[259,-40],[88,-70],[38,-118],[-7,-210]],[[16590,16139],[-62,-275],[115,-271]],[[16643,15593],[-175,-183],[-74,-1],[-121,118]],[[7774,10053],[-88,-183],[-31,-138],[-11,-233]],[[7644,9499],[-188,118],[-121,224]],[[17862,17689],[-173,-106],[-45,25],[-229,-19]],[[17131,18613],[120,10],[95,-38],[93,73],[94,279],[60,583]],[[18256,17078],[-225,-337],[-83,-51],[-61,-144],[-139,-130]],[[17748,16416],[-256,183],[-64,66]],[[16643,15593],[132,-309]],[[16775,15284],[-154,-71],[-134,-116],[-80,-129],[-15,-201]],[[16392,14767],[-118,235]],[[16274,15002],[36,206],[-12,117],[-52,98]],[[6753,8406],[90,-181],[78,-90],[15,-58],[-138,-258],[-3,-95],[61,-81]],[[6856,7643],[89,-360],[-2,-153],[51,-433],[148,-348]],[[7142,6349],[-305,-242],[-40,-7],[-116,110]],[[6681,6210],[-67,288],[19,102],[30,328],[-50,92],[-34,0],[-110,140],[-90,176],[-28,187]],[[6476,8450],[140,49],[137,-93]],[[5239,8346],[15,138],[-38,45]],[[5216,8529],[127,308],[21,186],[6,204]],[[6624,9154],[98,-65],[101,-389],[-2,-228],[-68,-66]],[[5216,8529],[-133,168],[-123,224],[-106,98],[-505,165],[-109,-48],[-19,-117]],[[4221,9019],[-52,125],[37,270],[292,784]],[[5929,6416],[-144,-550]],[[5785,5866],[-346,232],[-141,133],[-131,43],[-337,-93]],[[4830,6181],[-33,138]],[[4797,6319],[-75,316],[-53,173],[7,228],[83,294],[8,139],[-48,107],[183,320],[8,187]],[[4910,8083],[206,200],[100,246]],[[16274,15002],[-258,-59],[-131,3],[-82,87]],[[16392,14767],[-18,-92]],[[16374,14675],[-139,-133],[-139,-239],[-100,-2],[-94,89],[-156,317],[-140,168]],[[14930,14390],[41,-143],[-9,-87],[80,-210]],[[15042,13950],[-299,-274]],[[14743,13676],[-126,210],[-164,103],[-10,47],[-527,475],[-58,79],[-14,122]],[[15340,14497],[93,21],[55,-33],[88,-167]],[[15576,14318],[-83,-79],[2,-160],[-34,-84]],[[15461,13995],[-116,45],[-79,-52],[-112,19],[-112,-57]],[[9648,11343],[80,190],[18,125],[114,29],[174,130],[30,100],[126,27]],[[10190,11944],[252,-359]],[[10442,11585],[-223,-549],[-26,-287]],[[10193,10749],[-212,-82],[-140,132],[-33,127]],[[11163,13862],[200,-128],[130,-51],[2,-209],[92,-78]],[[11587,13396],[91,-479],[10,-166],[-62,-199]],[[11626,12552],[-94,-33],[-147,150],[-79,-4],[-94,-113],[-54,-148]],[[11158,12404],[-79,84],[-50,133],[-96,101],[-38,91],[-93,73]],[[11158,12404],[-7,-324],[-90,-309],[17,-76],[-39,-151]],[[11039,11544],[-57,37]],[[10982,11581],[-278,688]],[[10704,12269],[43,100],[14,314],[41,203]],[[10704,12269],[-89,239],[-183,177]],[[10432,12685],[-62,261],[8,295]],[[10432,12685],[-54,-57],[-62,-147],[-34,-142],[-90,-130]],[[10192,12209],[-27,219],[-41,82],[-77,-14],[-146,-188],[-303,-126]],[[9598,12182],[-64,202]],[[12481,13074],[-403,-3]],[[12078,13071],[-223,382]],[[11855,13453],[136,299],[83,322],[89,132],[108,44],[170,18]],[[12441,14268],[77,-74],[-64,-95],[-10,-137],[94,-247],[98,-119],[18,-72],[-28,-202],[-145,-248]],[[12481,13074],[37,-94],[12,-126],[70,-111],[120,-103]],[[12720,12640],[-28,-136],[22,-91],[55,-87]],[[12769,12326],[-19,-152],[41,-80],[-12,-70],[-91,-132],[-33,-272]],[[12655,11620],[-208,162],[-71,23],[-55,-24],[-90,112],[-29,124],[-109,253],[-190,183]],[[11903,12453],[121,209],[13,235],[52,108],[-11,66]],[[12441,14268],[14,102],[-59,155],[-13,173]],[[12506,14632],[22,-167],[88,-178],[100,-68],[88,-96],[104,-40],[155,-184]],[[13063,13899],[-40,-100],[-42,-208],[58,-127],[-63,-172],[102,-134]],[[13078,13158],[-82,-228],[-118,50],[-74,-94],[-84,-246]],[[11855,13453],[-268,-57]],[[9330,9905],[31,61],[5,105],[-77,157]],[[10193,10749],[185,17]],[[10378,10766],[82,-233],[-127,-125],[-32,-94],[72,22],[91,-168],[87,-219],[26,-198],[-105,-128],[-94,34]],[[10378,9657],[-151,-96],[-108,-154],[-77,-69],[-226,-46],[-51,40],[-70,182],[10,220],[-77,63],[-269,5],[-29,103]],[[10378,9657],[30,-280],[-73,-190],[23,-239],[36,-163],[92,-40],[63,13],[283,143]],[[10832,8901],[44,-225],[100,-114]],[[10976,8562],[-5,-132],[145,-369]],[[11116,8061],[-170,30],[-64,-70],[-155,12],[-91,-23],[-24,-205],[-29,-115],[-51,-101],[-154,-80],[-112,112],[-176,36]],[[10090,7657],[-29,261],[-89,339],[-146,205],[-150,298],[-150,215],[-136,41],[-244,-184],[-343,92],[-100,-10]],[[8703,8914],[-69,54],[-12,53],[-70,83]],[[8552,9104],[239,192],[26,98]],[[8817,9394],[332,212],[181,299]],[[9598,12182],[-33,-177],[-62,-128],[-29,-143],[-17,-220]],[[7142,6349],[51,-146],[-7,-258],[51,-153]],[[7237,5792],[-138,-110],[-167,-217],[-95,-232],[28,-156],[107,-192],[147,-158],[37,-116],[-89,-109]],[[6482,3941],[-372,449],[-28,199]],[[6082,4589],[-152,43],[-75,79],[-114,186],[-71,198],[7,151],[126,497],[-18,123]],[[6419,6218],[106,-153],[44,11],[39,85],[73,49]],[[7142,6349],[112,51],[145,-81],[153,-151],[97,-4],[71,96],[34,109],[-8,194]],[[7746,6563],[40,-19],[59,194]],[[7845,6738],[131,-199],[28,-116],[90,-159]],[[8094,6264],[0,-167],[-20,-123],[12,-63],[81,-41],[112,-126],[117,-269]],[[8396,5475],[-110,-52],[-101,-125],[-169,-95],[-259,-68]],[[7757,5135],[-145,-47]],[[7612,5088],[-220,317],[-155,387]],[[6082,4589],[-328,-268],[-96,-112],[-233,-134],[-115,-11],[-187,-132],[-142,-44],[-101,0],[-106,43],[-151,105]],[[4623,4036],[-73,277],[-62,126],[-222,245]],[[4266,4684],[74,238],[21,261],[41,163],[-80,393]],[[4322,5739],[299,165],[209,277]],[[4605,2785],[-68,51],[21,107],[-89,335],[-4,193],[-38,178],[58,226],[73,53],[65,108]],[[11903,12453],[-89,-43]],[[11814,12410],[-188,142]],[[12655,11620],[-15,-134],[-80,-126],[-27,-177]],[[12533,11183],[-112,-37],[-85,-113],[0,-263],[10,-77],[-54,-67]],[[11752,10755],[49,527],[-38,473],[51,210],[0,445]],[[10192,12209],[-2,-265]],[[8371,10002],[-59,-71],[4,-85],[91,-98],[-14,-117]],[[8393,9631],[-132,5],[-85,-63],[-151,-151],[-75,-53],[-147,-25]],[[7803,9344],[-13,123],[-146,32]],[[8729,7977],[60,67]],[[8789,8044],[147,22],[55,55],[187,-10],[204,-99],[126,2],[18,78],[75,-60],[178,-405],[138,-138]],[[9917,7489],[-117,-192],[-127,-109],[-64,-227],[-30,-364],[-33,-158],[16,-137],[37,-110]],[[9599,6192],[-4,-173],[-166,-48],[-19,-120],[56,-277],[-3,-240],[-43,-113],[-76,-50],[-80,27],[-126,-7]],[[9138,5191],[-127,150],[-18,95],[-68,109],[-78,200],[11,188],[48,220],[-103,229]],[[8803,6382],[-29,127],[19,215],[-87,266],[-27,196],[6,81],[-117,78],[17,182],[100,227],[44,223]],[[8729,7977],[-193,181],[-54,-3],[-94,-81],[-61,-123],[-103,-90],[-191,-8],[-91,104]],[[7942,7957],[-185,260],[-153,47],[-134,-35],[-41,-45],[4,-129],[-17,-188]],[[7416,7867],[-127,108],[-66,-5],[-142,-80],[-40,-122],[-185,-125]],[[7803,9344],[10,-114],[125,-115],[111,-45],[155,15],[130,65],[91,-66],[127,20]],[[8703,8914],[-30,-207],[79,-146],[48,-167],[-23,-77],[12,-273]],[[10090,7657],[-95,-124],[-78,-44]],[[7416,7867],[132,-248],[37,-239],[10,-160],[-30,-312],[44,-85],[19,-181],[118,-79]],[[8393,9631],[103,-79],[79,-22],[66,-134],[54,-18],[122,16]],[[11039,11544],[125,-187],[89,-77],[37,-84],[-35,-2],[-24,-107],[-1,-212],[-20,-164],[-37,-67],[-90,-40]],[[11083,10604],[-211,-41],[-207,124]],[[10665,10687],[47,250],[-9,205]],[[10703,11142],[99,62],[180,377]],[[9138,5191],[-13,-239],[71,-314]],[[9083,4436],[-687,1039]],[[8094,6264],[125,118],[30,75],[45,20],[83,-60],[243,-130],[53,0],[130,95]],[[10832,8901],[112,44],[-8,135],[90,52],[28,169]],[[11054,9301],[140,-104],[222,90]],[[11661,8846],[16,-107],[36,-56],[94,-52],[90,-116],[-27,-88],[-90,-15],[-484,181],[-320,-31]],[[12533,11183],[143,-93],[29,-129],[-15,-88],[-5,-353]],[[13078,13158],[182,-157],[49,-25],[263,19]],[[13572,12995],[137,-125],[49,-8],[55,-73],[44,-150],[46,-351],[18,-211],[-35,-218]],[[13886,11859],[-143,-15]],[[13743,11844],[-114,87],[-76,-39],[-659,302],[-125,132]],[[4910,8083],[-174,95],[-94,272],[-93,35],[-177,393],[-151,141]],[[13063,13899],[114,-81],[67,-126],[39,-137],[39,-41],[79,11],[89,-39],[36,-70],[-10,-125],[56,-296]],[[4221,9019],[-1,-98],[-68,-32],[-123,47],[-114,123],[-110,149],[-28,7],[-21,-111],[-75,-133],[-111,20],[-26,-137],[-98,10],[-83,78]],[[4322,5739],[-154,154],[-45,238],[-61,109],[-116,65],[-85,-7],[-107,-49],[-153,-142],[-67,-108],[-191,-209],[-38,-166]],[[3092,8031],[85,-184],[6,-55],[104,-129],[114,-89],[144,-253],[154,-200],[84,-39],[186,-207],[82,-129],[251,-268],[495,-159]],[[3966,4740],[97,88],[67,-11],[136,-133]],[[7612,5088],[-69,-122],[81,-202],[64,-436]],[[13743,11844],[-172,-311],[-168,-149],[-112,-122],[-69,-120],[14,-180],[52,-204],[114,-269],[47,-182],[48,-71],[89,-54],[170,62],[86,-87]],[[13782,9813],[-115,-121],[-67,-127],[-52,-44],[-112,47],[-32,-146],[64,-201],[38,-278]],[[13035,8882],[-317,122]],[[14084,7919],[127,337],[-27,57],[-254,-73]],[[13886,11859],[85,-56]],[[12683,7097],[-105,135],[-25,96],[-161,80],[-136,-15],[-59,-59],[1,-159],[-46,-59],[-84,120],[-56,-12],[-13,-75],[-109,-89],[3,-108]],[[11893,6952],[-221,181],[-146,194],[-93,180],[-45,137],[6,87],[49,114],[-9,101],[-145,-93],[-66,101],[-107,107]],[[10925,5311],[-237,278],[-73,204]],[[10615,5793],[3,279],[81,162],[63,75],[143,54],[70,154],[51,25],[165,-228],[107,-70]],[[10615,5793],[-73,-40],[-65,96],[-99,59],[-133,-97],[-76,23],[-51,59],[-65,217],[-122,96],[-332,-14]],[[10747,4963],[-156,2],[-117,49],[-118,-70],[-91,-186]],[[19130,16331],[-92,-33],[-94,44],[-86,-48],[-45,-185]],[[18635,16297],[-14,285],[-96,136],[20,188],[74,92]],[[17428,16665],[-33,-92],[44,-128],[-105,-8],[-103,-198]],[[17231,16239],[-61,-82],[-56,205],[-76,59],[-137,-232],[-87,57]],[[17231,16239],[70,-327],[-7,-77],[-73,-308]],[[16857,15102],[-82,182]],[[18635,16297],[-168,15],[-77,-129],[-15,-80],[41,-198]],[[18104,16114],[-85,108],[-271,194]],[[17849,15779],[-116,118],[-18,134],[-72,95],[-39,112],[-11,139],[87,-26],[68,65]],[[7845,6738],[-59,275],[24,439],[-28,275],[41,108],[119,122]],[[11054,9301],[-57,193],[-105,119],[-79,184],[-21,101],[34,184],[86,220],[114,116],[72,131]],[[11098,10549],[-15,55]],[[10378,10766],[117,-108],[170,29]],[[10703,11142],[-55,223],[-76,155],[-130,65]],[[15576,14318],[183,-335],[78,-270],[-12,-186],[85,-115],[-11,-77]],[[15657,13485],[-196,510]],[[16374,14675],[-5,-285],[61,-126]],[[16430,14264],[-64,-422]],[[16366,13842],[-1,-88],[-47,-96],[-200,-190]],[[14727,11808],[171,317],[49,201],[12,352],[-34,103],[-46,35],[-119,29],[-79,184],[20,79]],[[14701,13108],[560,-59],[97,-32],[115,-86]],[[14743,13676],[-64,-87],[50,-79],[2,-129],[-48,-166],[18,-107]],[[16366,13842],[254,-54]],[[16430,14264],[153,-64],[124,171],[46,111],[108,334]],[[10617,2884],[21,279],[145,335],[58,93],[74,56],[116,-26]],[[7757,5135],[140,-160],[220,-103],[122,-34],[77,-61],[15,-236],[-87,-382],[-39,-119],[-72,-99]]]}